Workbook

Sheet COMPANY
A1: COMPANY_NAME | B1: CATEGORY | C1: LOCATION | D1: FOUNDED_ON | E1: EXITED_ON | F1: CLOSED_ON | G1: REVENU_RANGE | H1: EMPLOYEE_NUMBER
A2: TangoMe | B2: Android, Apps, iOS, Messaging, Mobile | C2: Mountain View, California, United States | D2: Sep 9, 2009 | E2: — | F2: — | G2: $10M to $50M | H2: 101-250
A3: Zume Pizza | B3: Consumer, Food and Beverage, Food Delivery | C3: Mountain View, California, United States | D3: Sep 8, 2015 | E3: — | F3: Jan 2020 | G3: $50M to $100M | H3: 101-250
A4: LabCorp | B4: Biotechnology, Health Care, Hospital, Life Science, Medical | C4: Burlington, North Carolina, United States | D4: Sep 5, 1978 | E4: Jul 15, 1988 | F4: — | G4: $1B to $10B | H4: 10001+
A5: SoftBank | B5: Banking, Finance, Internet, Mobile, Telecommunications | C5: Tokyo, Tokyo, Japan | D5: Sep 3, 1981 | E5: May 14, 1999 | F5: — | G5: $10B+ | H5: 10001+
A6: Signal | B6: Analytics, Cloud Computing, Data Integration, Enterprise Software, Marketing, Marketing Automation, Project Management, SaaS | C6: Chicago, Illinois, United States | D6: Sep 26, 2009 | E6: Aug 17, 2020 | F6: — | G6: $10M to $50M | H6: 11-50
A7: DHL | B7: Logistics, Supply Chain Management | C7: Bonn, Nordrhein-Westfalen, Germany | D7: Sep 25, 1969 | E7: — | F7: — | G7: $50M to $100M | H7: 1-10
A8: Sprinklr | B8: Advertising Platforms, Analytics, Customer Service, Digital Marketing, Enterprise Software, Social CRM, Social Media, Social Media Advertising, Social Media Management, Software | C8: New York, New York, United States | D8: Sep 24, 2009 | E8: — | F8: — | G8: $100M to $500M | H8: 1001-5000
A9: KFC | B9: Food and Beverage, Restaurants, Retail | C9: Louisville, Kentucky, United States | D9: Sep 24, 1952 | E9: Jul 25, 1986 | F9: — | G9: $10B+ | H9: 10001+
A10: Confluent | B10: Analytics, Big Data, Cloud Data Services, Enterprise Software, Open Source, Software | C10: Mountain View, California, United States | D10: Sep 23, 2014 | E10: — | F10: — | G10: $10M to $50M | H10: 1001-5000
A11: Yandex | B11: Big Data, Developer Tools, Email, Information Technology, Mobile, Search Engine | C11: Moscow, Moscow City, Russian Federation | D11: Sep 23, 1997 | E11: May 24, 2011 | F11: — | G11: $500M to $1B | H11: 5001-10000
A12: ShearShare | B12: B2B, Beauty, Marketplace, Mobile, Mobile Apps, Sharing Economy | C12: Mckinney, Texas, United States | D12: Sep 2015 | E12: — | F12: — | G12: Less than $1M | H12: 11-50
... A1001: Schneider Electric | B1001: Electronics, Energy, Energy Management, Enterprise Software, Information Technology, Renewable Energy, Software | C1001: Rueil-malmaison, Ile-de-France, France | D1001: 1836 | E1001: — | F1001: — | G1001: $1B to $10B | H1001: 10001+

Sheet INVESTMENT
A1: COMPANY_NAME | B1: LOCATION | C1: FUNDING_TYPE | D1: MONEY_RAISED | E1: ANNOUNCED_DATE | F1: INVESTMENT_STAGE
A2: 1mg | B2: =_xlfn.XLOOKUP(INVESTMENT!A2475,COMPANY!A:A,COMPANY!C:C) -> San Francisco, California, United States | C2: Venture - Series Unknown | D2: ₹710,000,000 | E2: Jan 31, 2020 | F2: —
A3: 1mg | B3: =_xlfn.XLOOKUP(INVESTMENT!A252,COMPANY!A:A,COMPANY!C:C) -> Cyberport, Hong Kong Island, Hong Kong | C3: Series A | D3: $6,000,000 | E3: Apr 20, 2015 | F3: Early Stage Venture
A4: 1mg | B4: =_xlfn.XLOOKUP(INVESTMENT!A253,COMPANY!A:A,COMPANY!C:C) -> Cyberport, Hong Kong Island, Hong Kong | C4: Series A | D4: $6,000,000 | E4: Apr 20, 2015 | F4: Early Stage Venture
A5: 1mg | B5: =_xlfn.XLOOKUP(INVESTMENT!A2912,COMPANY!A:A,COMPANY!C:C) -> Chicago, Illinois, United States | C5: Debt Financing | D5: $17,800,000 | E5: Jul 3, 2020 | F5: —
A6: 1mg | B6: =_xlfn.XLOOKUP(INVESTMENT!A255,COMPANY!A:A,COMPANY!C:C) -> Cyberport, Hong Kong Island, Hong Kong | C6: Series B | D6: $16,000,000 | E6: Apr 20, 2016 | F6: Early Stage Venture
A7: 1mg | B7: =_xlfn.XLOOKUP(INVESTMENT!A40,COMPANY!A:A,COMPANY!C:C) -> London, England, United Kingdom | C7: Series B | D7: $13,800,000 | E7: Apr 1, 2016 | F7: Early Stage Venture
A8: 1mg | B8: =_xlfn.XLOOKUP(INVESTMENT!A222,COMPANY!A:A,COMPANY!C:C) -> San Francisco, California, United States | C8: Debt Financing | D8: $13,300,000 | E8: Apr 19, 2021 | F8: —
A9: 1mg | B9: =_xlfn.XLOOKUP(INVESTMENT!A2600,COMPANY!A:A,COMPANY!C:C) -> San Francisco, California, United States | C9: Series C | D9: $12,200,000 | E9: Jul 1, 2017 | F9: Late Stage Venture
A10: 1mg | B10: =_xlfn.XLOOKUP(INVESTMENT!A4406,COMPANY!A:A,COMPANY!C:C) -> Austin, Texas, United States | C10: Venture - Series Unknown | D10: — | E10: May 31, 2016 | F10: —
A11: 1mg | B11: =_xlfn.XLOOKUP(INVESTMENT!A4407,COMPANY!A:A,COMPANY!C:C) -> Shanghai, Shanghai, China | C11: Venture - Series Unknown | D11: — | E11: May 31, 2016 | F11: —
A12: 23andMe | B12: =_xlfn.XLOOKUP(INVESTMENT!A1424,COMPANY!A:A,COMPANY!C:C) -> London, England, United Kingdom | C12: Series F | D12: $82,500,000 | E12: Dec 29, 2020 | F12: Late Stage Venture
A13: 23andMe | B13: =_xlfn.XLOOKUP(INVESTMENT!A5286,COMPANY!A:A,COMPANY!C:C) -> San Francisco, California, United States | C13: Series A | D13: $8,953,320 | E13: Oct 3, 2007 | F13: Early Stage Venture
A14: 23andMe | B14: =_xlfn.XLOOKUP(INVESTMENT!A1353,COMPANY!A:A,COMPANY!C:C) -> London, England, United Kingdom | C14: Series D | D14: $50,000,000 | E14: Dec 21, 2012 | F14: Late Stage Venture
A15: 23andMe | B15: =_xlfn.XLOOKUP(INVESTMENT!A1354,COMPANY!A:A,COMPANY!C:C) -> London, England, United Kingdom | C15: Series D | D15: $50,000,000 | E15: Dec 21, 2012 | F15: Late Stage Venture
A16: 23andMe | B16: =_xlfn.XLOOKUP(INVESTMENT!A1355,COMPANY!A:A,COMPANY!C:C) -> London, England, United Kingdom | C16: Series D | D16: $50,000,000 | E16: Dec 21, 2012 | F16: Late Stage Venture
A17: 23andMe | B17: =_xlfn.XLOOKUP(INVESTMENT!A2834,COMPANY!A:A,COMPANY!C:C) -> New York, New York, United States | C17: Corporate Round | D17: $300,000,000 | E17: Jul 24, 2018 | F17: —
A18: 23andMe | B18: =_xlfn.XLOOKUP(INVESTMENT!A5867,COMPANY!A:A,COMPANY!C:C) -> Brooklyn, New York, United States | C18: Series F | D18: $250,000,000 | E18: Sep 5, 2017 | F18: Late Stage Venture
A19: 23andMe | B19: =_xlfn.XLOOKUP(INVESTMENT!A1388,COMPANY!A:A,COMPANY!C:C) -> San Francisco, California, United States | C19: Series B | D19: $14,200,000 | E19: Dec 23, 2009 | F19: Early Stage Venture
A20: 23andMe | B20: =_xlfn.XLOOKUP(INVESTMENT!A1389,COMPANY!A:A,COMPANY!C:C) -> San Francisco, California, United States | C20: Series B | D20: $14,200,000 | E20: Dec 23, 2009 | F20: Early Stage Venture
A21: 23andMe | B21: =_xlfn.XLOOKUP(INVESTMENT!A4945,COMPANY!A:A,COMPANY!C:C) -> San Francisco, California, United States | C21: Debt Financing | D21: — | E21: Nov 8, 2010 | F21: —
A22: 23andMe | B22: =_xlfn.XLOOKUP(INVESTMENT!A5198,COMPANY!A:A,COMPANY!C:C) -> Boston, Massachusetts, United States | C22: Series F | D22: — | E22: Oct 23, 2018 | F22: Late Stage Venture
A23: 360VUZ | B23: =_xlfn.XLOOKUP(INVESTMENT!A262,COMPANY!A:A,COMPANY!C:C) -> Cyberport, Hong Kong Island, Hong Kong | C23: Series A | D23: $7,093,000 | E23: Apr 20, 2020 | F23: Early Stage Venture
A24: 360VUZ | B24: =_xlfn.XLOOKUP(INVESTMENT!A1454,COMPANY!A:A,COMPANY!C:C) -> Burlington, Massachusetts, United States | C24: Seed | D24: $1,350,000 | E24: Dec 30, 2017 | F24: Seed
A25: 360VUZ | B25: =_xlfn.XLOOKUP(INVESTMENT!A2340,COMPANY!A:A,COMPANY!C:C) -> Mountain View, California, United States | C25: Seed | D25: — | E25: Jan 22, 2019 | F25: Seed
A26: 4D Molecular Therapeutics | B26: =_xlfn.XLOOKUP(INVESTMENT!A5871,COMPANY!A:A,COMPANY!C:C) -> Gurgaon, Haryana, India | C26: Series B | D26: $90,000,000 | E26: Sep 5, 2018 | F26: Early Stage Venture
A27: 4D Molecular Therapeutics | B27: =_xlfn.XLOOKUP(INVESTMENT!A3170,COMPANY!A:A,COMPANY!C:C) -> New York, New York, United States | C27: Series C | D27: $75,000,000 | E27: Jun 16, 2020 | F27: Late Stage Venture
A28: 4D Molecular Therapeutics | B28: =_xlfn.XLOOKUP(INVESTMENT!A633,COMPANY!A:A,COMPANY!C:C) -> Berkeley, California, United States | C28: Venture - Series Unknown | D28: $6,999,995 | E28: Aug 13, 2015 | F28: —
A29: 908 Devices | B29: =_xlfn.XLOOKUP(INVESTMENT!A840,COMPANY!A:A,COMPANY!C:C) -> New York, New York, United States | C29: Series B | D29: $7,000,000 | E29: Aug 27, 2013 | F29: Early Stage Venture
A30: 908 Devices | B30: =_xlfn.XLOOKUP(INVESTMENT!A841,COMPANY!A:A,COMPANY!C:C) -> New York, New York, United States | C30: Series B | D30: $7,000,000 | E30: Aug 27, 2013 | F30: Early Stage Venture
A31: 908 Devices | B31: =_xlfn.XLOOKUP(INVESTMENT!A3610,COMPANY!A:A,COMPANY!C:C) -> Seattle, Washington, United States | C31: Series D | D31: $20,000,000 | E31: Mar 15, 2017 | F31: Late Stage Venture
A32: 908 Devices | B32: =_xlfn.XLOOKUP(INVESTMENT!A3611,COMPANY!A:A,COMPANY!C:C) -> Seattle, Washington, United States | C32: Series D | D32: $20,000,000 | E32: Mar 15, 2017 | F32: Late Stage Venture
A33: 908 Devices | B33: =_xlfn.XLOOKUP(INVESTMENT!A398,COMPANY!A:A,COMPANY!C:C) -> San Francisco, California, United States | C33: Series E | D33: $17,500,000 | E33: Apr 29, 2019 | F33: Late Stage Venture
A34: 908 Devices | B34: =_xlfn.XLOOKUP(INVESTMENT!A4464,COMPANY!A:A,COMPANY!C:C) -> New York, New York, United States | C34: Series C | D34: $11,600,000 | E34: May 6, 2015 | F34: Late Stage Venture
A35: 908 Devices | B35: =_xlfn.XLOOKUP(INVESTMENT!A3609,COMPANY!A:A,COMPANY!C:C) -> Seattle, Washington, United States | C35: Debt Financing | D35: — | E35: Mar 15, 2017 | F35: —
A36: Aave | B36: =_xlfn.XLOOKUP(INVESTMENT!A3001,COMPANY!A:A,COMPANY!C:C) -> Burlingame, California, United States | C36: Initial Coin Offering | D36: $4,500,000 | E36: Jul 8, 2020 | F36: —
A37: Aave | B37: =_xlfn.XLOOKUP(INVESTMENT!A2702,COMPANY!A:A,COMPANY!C:C) -> Louisville, Kentucky, United States | C37: Initial Coin Offering | D37: $3,000,000 | E37: Jul 15, 2020 | F37: —
A38: Aave | B38: =_xlfn.XLOOKUP(INVESTMENT!A5070,COMPANY!A:A,COMPANY!C:C) -> San Francisco, California, United States | C38: Venture - Series Unknown | D38: $25,000,000 | E38: Oct 12, 2020 | F38: —
A39: Aave | B39: =_xlfn.XLOOKUP(INVESTMENT!A4837,COMPANY!A:A,COMPANY!C:C) -> New York, New York, United States | C39: Initial Coin Offering | D39: $16,500,000 | E39: Nov 25, 2017 | F39: —
A40: Aave | B40: =_xlfn.XLOOKUP(INVESTMENT!A2461,COMPANY!A:A,COMPANY!C:C) -> Seattle, Washington, United States | C40: Secondary Market | D40: — | E40: Jan 30, 2021 | F40: —
A41: Aave | B41: =_xlfn.XLOOKUP(INVESTMENT!A2610,COMPANY!A:A,COMPANY!C:C) -> Stockholm, Stockholms Lan, Sweden | C41: Initial Coin Offering | D41: — | E41: Jul 1, 2020 | F41: —
A42: AbCellera Biologics | B42: =_xlfn.XLOOKUP(INVESTMENT!A441,COMPANY!A:A,COMPANY!C:C) -> San Francisco, California, United States | C42: Venture - Series Unknown | D42: $817,878 | E42: Apr 4, 2017 | F42: —
A43: AbCellera Biologics | B43: =_xlfn.XLOOKUP(INVESTMENT!A3595,COMPANY!A:A,COMPANY!C:C) -> Paris, Ile-de-France, France | C43: Grant | D43: $4,800,000 | E43: Mar 14, 2019 | F43: —
A44: AbCellera Biologics | B44: =_xlfn.XLOOKUP(INVESTMENT!A4387,COMPANY!A:A,COMPANY!C:C) -> London, England, United Kingdom | C44: Grant | D44: $175,600,000 | E44: May 3, 2020 | F44: —
A45: AbCellera Biologics | B45: =_xlfn.XLOOKUP(INVESTMENT!A4347,COMPANY!A:A,COMPANY!C:C) -> Palo Alto, California, United States | C45: Series B | D45: $105,000,000 | E45: May 27, 2020 | F45: Early Stage Venture
A46: AbCellera Biologics | B46: =_xlfn.XLOOKUP(INVESTMENT!A5788,COMPANY!A:A,COMPANY!C:C) -> Beijing, Beijing, China | C46: Series A | D46: $10,000,000 | E46: Sep 27, 2018 | F46: Early Stage Venture
A47: AbCellera Biologics | B47: =_xlfn.XLOOKUP(INVESTMENT!A978,COMPANY!A:A,COMPANY!C:C) -> London, England, United Kingdom | C47: Seed | D47: — | E47: Aug 9, 2014 | F47: Seed
A48: AbCellera Biologics | B48: =_xlfn.XLOOKUP(INVESTMENT!A2075,COMPANY!A:A,COMPANY!C:C) -> San Francisco, California, United States | C48: Venture - Series Unknown | D48: — | E48: Jan 1, 2015 | F48: —
A49: AbCellera Biologics | B49: =_xlfn.XLOOKUP(INVESTMENT!A2294,COMPANY!A:A,COMPANY!C:C) -> Mountain View, California, United States | C49: Grant | D49: — | E49: Jan 19, 2017 | F49: —
A50: AbCellera Biologics | B50: =_xlfn.XLOOKUP(INVESTMENT!A5783,COMPANY!A:A,COMPANY!C:C) -> Beijing, Beijing, China | C50: Grant | D50: — | E50: Sep 27, 2013 | F50: —
A51: AbCellera Biologics | B51: =_xlfn.XLOOKUP(INVESTMENT!A5787,COMPANY!A:A,COMPANY!C:C) -> Beijing, Beijing, China | C51: Series A | D51: — | E51: Sep 27, 2018 | F51: Early Stage Venture
A52: Abnormal Security | B52: =_xlfn.XLOOKUP(INVESTMENT!A4738,COMPANY!A:A,COMPANY!C:C) -> Hawthorne, California, United States | C52: Series B | D52: $50,000,000 | E52: Nov 18, 2020 | F52: Early Stage Venture
A53: Abnormal Security | B53: =_xlfn.XLOOKUP(INVESTMENT!A4759,COMPANY!A:A,COMPANY!C:C) -> Hawthorne, California, United States | C53: Series A | D53: $24,000,000 | E53: Nov 19, 2019 | F53: Early Stage Venture
A54: Accenture | B54: =_xlfn.XLOOKUP(INVESTMENT!A5011,COMPANY!A:A,COMPANY!C:C) -> New York, New York, United States | C54: Grant | D54: $6,000,000 | E54: Oct 1, 2018 | F54: —
A55: Accenture | B55: =_xlfn.XLOOKUP(INVESTMENT!A5012,COMPANY!A:A,COMPANY!C:C) -> New York, New York, United States | C55: Grant | D55: $6,000,000 | E55: Oct 1, 2018 | F55: —
A56: Aceable | B56: =_xlfn.XLOOKUP(INVESTMENT!A1259,COMPANY!A:A,COMPANY!C:C) -> Las Condes, Region Metropolitana, Chile | C56: Series C | D56: $50,000,000 | E56: Dec 17, 2020 | F56: Late Stage Venture
A57: Aceable | B57: =_xlfn.XLOOKUP(INVESTMENT!A5718,COMPANY!A:A,COMPANY!C:C) -> Issy-les-moulineaux, Ile-de-France, France | C57: Series A | D57: $4,000,000 | E57: Sep 23, 2016 | F57: Early Stage Venture
A58: Aceable | B58: =_xlfn.XLOOKUP(INVESTMENT!A5099,COMPANY!A:A,COMPANY!C:C) -> Palo Alto, California, United States | C58: Seed | D58: — | E58: Oct 15, 2013 | F58: Seed
A59: Aclima | B59: =_xlfn.XLOOKUP(INVESTMENT!A4761,COMPANY!A:A,COMPANY!C:C) -> Hawthorne, California, United States | C59: Series B | D59: $40,000,000 | E59: Nov 19, 2020 | F59: Early Stage Venture
A60: Aclima | B60: =_xlfn.XLOOKUP(INVESTMENT!A3319,COMPANY!A:A,COMPANY!C:C) -> Shanghai, Shanghai, China | C60: Series A | D60: $24,000,000 | E60: Jun 26, 2018 | F60: Early Stage Venture
A61: Acorns | B61: =_xlfn.XLOOKUP(INVESTMENT!A3567,COMPANY!A:A,COMPANY!C:C) -> Houston, Texas, United States | C61: Series B | D61: $6,160,000 | E61: Mar 12, 2014 | F61: Early Stage Venture
A62: Acorns | B62: =_xlfn.XLOOKUP(INVESTMENT!A3568,COMPANY!A:A,COMPANY!C:C) -> Houston, Texas, United States | C62: Series B | D62: $6,160,000 | E62: Mar 12, 2014 | F62: Early Stage Venture
A63: Acorns | B63: =_xlfn.XLOOKUP(INVESTMENT!A270,COMPANY!A:A,COMPANY!C:C) -> San Francisco, California, United States | C63: Series D | D63: $35,000,000 | E63: Apr 21, 2016 | F63: Late Stage Venture
A64: Acorns | B64: =_xlfn.XLOOKUP(INVESTMENT!A2774,COMPANY!A:A,COMPANY!C:C) -> Mountain View, California, United States | C64: Series D | D64: $35,000,000 | E64: Jul 20, 2017 | F64: Late Stage Venture
A65: Acorns | B65: =_xlfn.XLOOKUP(INVESTMENT!A1718,COMPANY!A:A,COMPANY!C:C) -> Redwood City, California, United States | C65: Series C | D65: $23,000,000 | E65: Feb 15, 2015 | F65: Late Stage Venture
A66: Acorns | B66: =_xlfn.XLOOKUP(INVESTMENT!A1719,COMPANY!A:A,COMPANY!C:C) -> Redwood City, California, United States | C66: Series C | D66: $23,000,000 | E66: Feb 15, 2015 | F66: Late Stage Venture
A67: Acorns | B67: =_xlfn.XLOOKUP(INVESTMENT!A4986,COMPANY!A:A,COMPANY!C:C) -> Washington, District of Columbia, United States | C67: Series A | D67: $2,500,000 | E67: Oct 1, 2013 | F67: Early Stage Venture
A68: Acorns | B68: =_xlfn.XLOOKUP(INVESTMENT!A2181,COMPANY!A:A,COMPANY!C:C) -> New York, New York, United States | C68: Venture - Series Unknown | D68: — | E68: Jan 12, 2018 | F68: —
A69: Acronis | B69: =_xlfn.XLOOKUP(INVESTMENT!A4437,COMPANY!A:A,COMPANY!C:C) -> San Francisco, California, United States | C69: Private Equity | D69: $250,000,000 | E69: May 4, 2021 | F69: Private Equity
A70: Acronis | B70: =_xlfn.XLOOKUP(INVESTMENT!A1985,COMPANY!A:A,COMPANY!C:C) -> San Francisco, California, United States | C70: Venture - Series Unknown | D70: $11,000,000 | E70: Jan 1, 2004 | F70: —
A71: Actifio | B71: =_xlfn.XLOOKUP(INVESTMENT!A3929,COMPANY!A:A,COMPANY!C:C) -> Bangalore, Karnataka, India | C71: Series D | D71: $50,000,000 | E71: Mar 6, 2013 | F71: Late Stage Venture
A72: Actifio | B72: =_xlfn.XLOOKUP(INVESTMENT!A782,COMPANY!A:A,COMPANY!C:C) -> San Francisco, California, United States | C72: Debt Financing | D72: $41,000,000 | E72: Aug 22, 2018 | F72: —
A73: Actifio | B73: =_xlfn.XLOOKUP(INVESTMENT!A2564,COMPANY!A:A,COMPANY!C:C) -> San Francisco, California, United States | C73: Seed | D73: $4,000,000 | E73: Jul 1, 2009 | F73: Seed
A74: Actifio | B74: =_xlfn.XLOOKUP(INVESTMENT!A2565,COMPANY!A:A,COMPANY!C:C) -> San Francisco, California, United States | C74: Seed | D74: $4,000,000 | E74: Jul 1, 2009 | F74: Seed
A75: Actifio | B75: =_xlfn.XLOOKUP(INVESTMENT!A1481,COMPANY!A:A,COMPANY!C:C) -> Beijing, Beijing, China | C75: Series C | D75: $33,500,000 | E75: Dec 5, 2011 | F75: Late Stage Venture
A76: Actifio | B76: =_xlfn.XLOOKUP(INVESTMENT!A5697,COMPANY!A:A,COMPANY!C:C) -> Geneva, Geneve, Switzerland | C76: Series B | D76: $16,000,000 | E76: Sep 22, 2010 | F76: Early Stage Venture
A77: Actifio | B77: =_xlfn.XLOOKUP(INVESTMENT!A5698,COMPANY!A:A,COMPANY!C:C) -> Geneva, Geneve, Switzerland | C77: Series B | D77: $16,000,000 | E77: Sep 22, 2010 | F77: Early Stage Venture
A78: Actifio | B78: =_xlfn.XLOOKUP(INVESTMENT!A3743,COMPANY!A:A,COMPANY!C:C) -> Andheri, Maharashtra, India | C78: Series E | D78: $100,000,000 | E78: Mar 23, 2014 | F78: Late Stage Venture
A79: ActiveCampaign | B79: =_xlfn.XLOOKUP(INVESTMENT!A278,COMPANY!A:A,COMPANY!C:C) -> New York, New York, United States | C79: Series C | D79: $240,000,000 | E79: Apr 21, 2021 | F79: Late Stage Venture
A80: ActiveCampaign | B80: =_xlfn.XLOOKUP(INVESTMENT!A2418,COMPANY!A:A,COMPANY!C:C) -> Cambridge, Massachusetts, United States | C80: Series B | D80: $100,000,000 | E80: Jan 28, 2020 | F80: Early Stage Venture
A81: Ada | B81: =_xlfn.XLOOKUP(INVESTMENT!A1282,COMPANY!A:A,COMPANY!C:C) -> Seoul, Seoul-t'ukpyolsi, South Korea | C81: Series A | D81: CA$19,000,000 | E81: Dec 18, 2018 | F81: Early Stage Venture
A82: Ada | B82: =_xlfn.XLOOKUP(INVESTMENT!A3678,COMPANY!A:A,COMPANY!C:C) -> San Francisco, California, United States | C82: Series B | D82: $44,000,000 | E82: Mar 19, 2020 | F82: Early Stage Venture
A83: Ada | B83: =_xlfn.XLOOKUP(INVESTMENT!A2775,COMPANY!A:A,COMPANY!C:C) -> Mountain View, California, United States | C83: Seed | D83: $2,500,000 | E83: Jul 20, 2017 | F83: Seed
A84: Ada | B84: =_xlfn.XLOOKUP(INVESTMENT!A4482,COMPANY!A:A,COMPANY!C:C) -> San Francisco, California, United States | C84: Series C | D84: $130,000,000 | E84: May 7, 2021 | F84: Late Stage Venture
A85: Ada | B85: =_xlfn.XLOOKUP(INVESTMENT!A2088,COMPANY!A:A,COMPANY!C:C) -> Daly City, California, United States | C85: Pre-Seed | D85: — | E85: Jan 1, 2016 | F85: Seed
A86: Ada | B86: =_xlfn.XLOOKUP(INVESTMENT!A3594,COMPANY!A:A,COMPANY!C:C) -> Redwood Shores, California, United States | C86: Pre-Seed | D86: — | E86: Mar 14, 2018 | F86: Seed
A87: Ada | B87: =_xlfn.XLOOKUP(INVESTMENT!A4341,COMPANY!A:A,COMPANY!C:C) -> Palo Alto, California, United States | C87: Pre-Seed | D87: — | E87: May 27, 2014 | F87: Seed
A88: AdaptHealth | B88: =_xlfn.XLOOKUP(INVESTMENT!A4892,COMPANY!A:A,COMPANY!C:C) -> Millbrae, California, United States | C88: Venture - Series Unknown | D88: $2,000,000 | E88: Nov 30, 2017 | F88: —
A89: AdaptHealth | B89: =_xlfn.XLOOKUP(INVESTMENT!A4893,COMPANY!A:A,COMPANY!C:C) -> Millbrae, California, United States | C89: Venture - Series Unknown | D89: $2,000,000 | E89: Nov 30, 2017 | F89: —
A90: Addepar | B90: =_xlfn.XLOOKUP(INVESTMENT!A4092,COMPANY!A:A,COMPANY!C:C) -> Seattle, Washington, United States | C90: Series C | D90: $50,000,000 | E90: May 12, 2014 | F90: Late Stage Venture
A91: Addepar | B91: =_xlfn.XLOOKUP(INVESTMENT!A4739,COMPANY!A:A,COMPANY!C:C) -> Hawthorne, California, United States | C91: Series E | D91: $117,000,000 | E91: Nov 18, 2020 | F91: Late Stage Venture
A92: Addepar | B92: =_xlfn.XLOOKUP(INVESTMENT!A2476,COMPANY!A:A,COMPANY!C:C) -> Noida, Uttar Pradesh, India | C92: Convertible Note | D92: — | E92: Jan 4, 2014 | F92: —
A93: Adjust | B93: =_xlfn.XLOOKUP(INVESTMENT!A5900,COMPANY!A:A,COMPANY!C:C) -> Foster City, California, United States | C93: Series C | D93: $7,600,000 | E93: Sep 8, 2014 | F93: Late Stage Venture
A94: Adjust | B94: =_xlfn.XLOOKUP(INVESTMENT!A3232,COMPANY!A:A,COMPANY!C:C) -> Berlin, Berlin, Germany | C94: Series B | D94: $4,300,000 | E94: Jun 20, 2013 | F94: Early Stage Venture
A95: Adjust | B95: =_xlfn.XLOOKUP(INVESTMENT!A4297,COMPANY!A:A,COMPANY!C:C) -> Los Gatos, California, United States | C95: Series A | D95: — | E95: May 24, 2012 | F95: Early Stage Venture
A96: Adyen | B96: =_xlfn.XLOOKUP(INVESTMENT!A1213,COMPANY!A:A,COMPANY!C:C) -> New York, New York, United States | C96: Series B | D96: $250,000,000 | E96: Dec 16, 2014 | F96: Early Stage Venture
A97: Adyen | B97: =_xlfn.XLOOKUP(INVESTMENT!A5832,COMPANY!A:A,COMPANY!C:C) -> Austin, Texas, United States | C97: Venture - Series Unknown | D97: — | E97: Sep 30, 2015 | F97: —
A98: Aerobotics | B98: =_xlfn.XLOOKUP(INVESTMENT!A572,COMPANY!A:A,COMPANY!C:C) -> Boston, Massachusetts, United States | C98: Seed | D98: ZAR8,000,000 | E98: Aug 1, 2017 | F98: Seed
A99: Aerobotics | B99: =_xlfn.XLOOKUP(INVESTMENT!A1123,COMPANY!A:A,COMPANY!C:C) -> Sunnyvale, California, United States | C99: Series B | D99: ZAR253,000,000 | E99: Dec 11, 2020 | F99: Early Stage Venture
A100: Aerobotics | B100: =_xlfn.XLOOKUP(INVESTMENT!A4250,COMPANY!A:A,COMPANY!C:C) -> Menlo Park, California, United States | C100: Venture - Series Unknown | D100: ZAR100,000,000 | E100: May 20, 2020 | F100: —
...

Sheet ACQUISITION
A1: COMPANY_NAME | B1: ACQUIREE_NAME | C1: ANNOUNCED_DATE | D1: PRICE | E1: ACQUISITION_TYPE
A2: 1mg | B2: Dawailelo | C2: Sep 1, 2017 | D2: — | E2: Acquisition
A3: 1mg | B3: Medd.in | C3: Jul 5, 2016 | D3: — | E3: Acquisition
A4: 23andMe | B4: Virgin Group | C4: Feb 5, 2021 | D4: — | E4: Merger
A5: 23andMe | B5: CureTogether | C5: Jul 10, 2012 | D5: — | E5: —
A6: AbCellera Biologics | B6: Dualogics - OrthoMab | C6: Aug 20, 2020 | D6: — | E6: Acquisition
A7: AbCellera Biologics | B7: Trianni | C7: Nov 18, 2020 | D7: $90,000,000 | E7: Acquisition
A8: AbCellera Biologics | B8: Lineage Biosciences | C8: Aug 1, 2018 | D8: — | E8: Acquisition
A9: Accenture | B9: AppsPro | C9: May 3, 2021 | D9: — | E9: Acquisition
A10: Accenture | B10: AppsPro | C10: May 3, 2021 | D10: — | E10: Acquisition
A11: Accenture | B11: BUSINET SYSTEM | C11: Feb 1, 2021 | D11: — | E11: Acquisition
A12: Accenture | B12: Cirrus | C12: Mar 1, 2021 | D12: — | E12: Acquisition
... A5290: Zuora | B5290: Frontleaf | C5290: May 20, 2015 | D5290: — | E5290: Acquisition

Sheet EMPLOYEE
A1: EMPLOYEE_MD5 | B1: JOB_TITLES | C1: COMPANY_NAME | D1: ATTENDED_SCHOOLS
A2: 1360e802a0514901cfe81e905d533168 | B2: Chief Operating Officer | C2: 1mg
A3: 4a7e3c46f6f02bc649adf89d8af78590 | B3: Co-Founder and CEO | C3: 1mg | D3: Harvard Business School Indian Institute of Technology Delhi
A4: 4e465c8ae639d50a866c7ba6aa584e82 | B4: CEO & Co-Founder | C4: 1mg | D4: Indian Institute of Technology Delhi Stanford University
A5: 6910ff251504d8ed442de572a92d2ec1 | B5: Co-Founder | C5: 1mg
A6: a0ca5d14863b0a86ff79e2fef87cc89e | B6: Business Development & Marketing Manager | C6: 1mg | D6: Shri Ramdeobaba College of Engineering and Management
A7: d93ed2e1cef9b1a647afcc7ce5f55170 | B7: Senior UX Designer | C7: 1mg | D7: Indian Institute of Technology Kanpur
A8: dc43866eddb6a7dc5384d72b84b341d3 | B8: Consultant | C8: 1mg | D8: Dr. K.N.Modi institute of Engineering & Technology
A9: 0a474afac723e6fb2f00032bae24601d | B9: Privacy and Data Protection Counsel | C9: 23andMe
A10: 0f1fad3a7abc3187fed777b99d3daff3 | B10: Chief Legal and Regulatory Officer | C10: 23andMe | D10: University of California Hastings College of Law
A11: 1df0182bd95ab262d23ffdc194c5f882 | B11: Vice President, Computational Biology | C11: 23andMe
A12: 38bc7b30fdb653fa36eb488df9272620 | B12: Senior Scientist Statistical Genetics, Health R+D | C12: 23andMe | D12: The University of Memphis University of California, Los Angeles (UCLA)
A13: 6e42990ec9f13f9e1662998ab9842cd5 | B13: Director & Research Infrastructure | C13: 23andMe
A14: 73c5e9448c15434cae2661b4f610e97c | B14: Chief Science Officer and Head of Therapeutics | C14: 23andMe | D14: Caltech - California Institute of Technology University of Wisconsin - Madison
A15: 9485c49e6bb738b8eba417fa8a19bb54 | B15: Co-Founder and CEO | C15: 23andMe | D15: Yale University
A16: c89d9316ccfee139692d1f6945be2bf7 | B16: Vice President, Research | C16: 23andMe | D16: Stanford University University of California, San Francisco
A17: a50c46df4404d961976a414997746f68 | B17: Co-Founder | C17: 360VUZ
A18: 1d4d8f0246772206796b8e54862c5e0c | B18: Co-Founder, President & CEO | C18: 4D Molecular Therapeutics
A19: 17e4e3de2309e367b717970614d7cd92 | B19: Co-Founder | C19: 908 Devices | D19: University of Strathclyde
A20: 18355614c3653f42ba6deef5472f0c77 | B20: Science Founder | C20: 908 Devices | D20: Indiana University
A21: 26aa094998990d8b644eef80fea4418a | B21: VP of Sales | C21: 908 Devices
A22: 3da6864541a01e9e1990fd9270f20743 | B22: Co-founder & CEO | C22: 908 Devices | D22: University of Colorado
A23: 45c40d841cbe0553f65388fd9426385c | B23: Co-Founder and VP of Business Development and Marketing | C23: 908 Devices
A24: 511bd8429159f3385d4e40c4775d3f0e | B24: Co-Founder | C24: 908 Devices
A25: 98e25847ac411c1b50475be7c1ab1f90 | B25: Co-Founder | C25: 908 Devices
A26: b7af8dbf5d00e4202de0739b2ce87974 | B26: Co-Founder | C26: 908 Devices
A27: d83fface22f39a038d46ddc048e25822 | B27: Co-Founder | C27: 908 Devices
A28: f1403614138d085b5f55dc1c8a5a2497 | B28: Co-Founder & CTO | C28: 908 Devices | D28: Brandon University Dalhousie University
A29: 768305055b03932f4ffe14d676aa4058 | B29: User Success Manager | C29: Aave
A30: 8fbb11d09f061fb0866976a942ca5f37 | B30: CEO & Founder | C30: Aave
A31: a0048e0cbf4d417f4dfa8110c9959f6f | B31: CEO | C31: AbCellera Biologics
A32: a158da117d28703cd242fb7bea7e7ac5 | B32: Co-Founder & Director | C32: AbCellera Biologics
A33: f00d00b8ae73e22f72cc573776f4705e | B33: Co-Founder | C33: AbCellera Biologics | D33: Claude Bernard University Lyon 1
A34: 9360e358428e7fff731e98119b5715b4 | B34: Vice President of Marketing | C34: Abnormal Security
A35: 9a2eabbd36ca3c9ea611a5a368aee045 | B35: CEO & Co-founder | C35: Abnormal Security
A36: bea99e96a8a994abdb44bdc404135810 | B36: Head of Engineering | C36: Abnormal Security
A37: f075c4b87899cd89a505452ed7016873 | B37: Region Manager - Enterprise Sales | C37: Abnormal Security
A38: f8226dd2f110443f9c5e4d3f1e321e02 | B38: CTO & Co-Founder | C38: Abnormal Security
A39: 0057e240c373870fbbd99210abaab372 | B39: Managing Director | C39: Accenture
A40: 00bab153925406e4905fb24b235205ac | B40: Manager for Accenture Information Management Services | C40: Accenture
A41: 01890c903d40de098a68a5ba54af5e4a | B41: IT Sourcing & Procurement Lead | C41: Accenture | D41: Columbia Business School Miami University
A42: 048a6e99984b534850e7d1504fc3bc57 | B42: Senior Managing Director | C42: Accenture
A43: 04ed23c90010ddd12d997985555dc523 | B43: Group Technology Officer | C43: Accenture
A44: 058156b8c400e4e8c1b7b9084f4c607f | B44: Specialist | C44: Accenture | D44: British Columbia Institute of Technology Simon Fraser University VanArts
A45: 06b914429c0e9369a7208900c468bd8a | B45: Blockchain Architect | C45: Accenture
A46: 0836e6eae318e5bf9ba145047021b625 | B46: Managing Director | C46: Accenture
A47: 0999ac530fc24d9f158ea0052d60bd5c | B47: Managing Director of Management Consulting | C47: Accenture
A48: 0a001183b9c60ff9170625d6284034a7 | B48: Managing Director | C48: Accenture
A49: 0a29522f8a483585dfcee0fc30cb14b3 | B49: Managing Director for Communications, Media & Technology (CMT) Africa | C49: Accenture
A50: 0a6cfa0785d5af963f72e3763fc3555b | B50: Digital Marketing Analytics Lead | C50: Accenture | D50: Saint Xavier University
A51: 0aa1e6a0585ab2e28895ed8066fdea30 | B51: Director | C51: Accenture | D51: University of Southampton University of Surrey
A52: 0b2dc1e1686204819043e3761a3d69f0 | B52: Senior Principal | C52: Accenture
A53: 0b34c3d91c04391b2ebb9efedd70488e | B53: Senior Manager | C53: Accenture
A54: 0d444f03540414d24a7af44c4fc02aa6 | B54: R&D Manager, Immersive Technology | C54: Accenture
A55: 0dac30eaf06fd691e548581dc3edb715 | B55: DMP Practice Lead | C55: Accenture | D55: Duke University Stanford University
A56: 0e1381ace7a6de63b48597d67ac7ff45 | B56: Senior Manager, Residential Mortgage and Consumer Lending Consulting Practice, North America | C56: Accenture
A57: 0e5a7d7c0bf06a3d4ac7df64237a134c | B57: partner | C57: Accenture | D57: Cass Business School
A58: 107a705c3e4f3ea56db664a54414b0fc | B58: Managing Director | C58: Accenture
A59: 11fee105f6bfd272bcedab63e49d26b0 | B59: Finance Director, Technology | C59: Accenture
A60: 120a29f7dfa5d9b6b707884753d04843 | B60: Senior Data Insights R&D Manager | C60: Accenture
A61: 127ef07125d44922c60885cac3a185fb | B61: Managing Director | C61: Accenture
A62: 138bafbc6a05b297b10ee3844e7fff26 | B62: Managing Director | C62: Accenture | D62: University of Virginia Darden School of Business Washington University in St. Louis
A63: 13947751f7843d16480b92c64ca15770 | B63: Chairman | C63: Accenture
A64: 14984d4f2ecfb2c496eacca4ff2d12ee | B64: Managing Director | C64: Accenture
A65: 172b91ce46d811636624127800b23146 | B65: Technology Consulting Analyst | C65: Accenture
A66: 1730688c0c475d0404940d66395a1b6c | B66: Senior Managing Director Communication, Media and Technology | C66: Accenture
A67: 18e9d0dc5373d9b5ef3ca031a287eac2 | B67: Managing Director | C67: Accenture
A68: 18f855f0c82ac2c66c220c8459ad73ec | B68: Full Stack Developer. | C68: Accenture
A69: 19443ad2f974b68f5f18490d8d658e80 | B69: Principal Director & Chief Data Scientist | C69: Accenture | D69: Carnegie Mellon University
A70: 19583c9a11198d4b3c10a11f7355d379 | B70: Managing Director - Management Consulting Lead - Middle East & Turkey | C70: Accenture
A71: 1ad31aefb5f4682453578bedae06d4f2 | B71: Interim CEO | C71: Accenture
A72: 1aecd51dc2d0ddbf955049670ee22bf7 | B72: Software Engineering Analyst | C72: Accenture
A73: 1e3b64ea1f7375b4604c4b657948a15e | B73: Creative Director (Liquid Studio London) | C73: Accenture
A74: 1e82422ec35ff275b32908024046d8ae | B74: Digital Customer Research and Development, Lead | C74: Accenture
A75: 1ed70a60ec8be0067b6174a5171f1fe5 | B75: Senior IoT & AI lead | C75: Accenture | D75: University of California, Santa Cruz
A76: 20a2a15cd662a91c038f4acbc7351ffb | B76: Senior Manager, Social Media Practice Lead - North America | C76: Accenture
A77: 244dfa13744353ea9a92ac721286de51 | B77: Managing Director, NA Lead Digital Productions & Operations | C77: Accenture
A78: 253109d764999ac0ebe82c03d4d6926d | B78: Senior Manager - Sustainability Services | C78: Accenture
A79: 255893256ef9bba5355524cbdf946ae7 | B79: Senior Manager | C79: Accenture
A80: 25b8768af9fc6443817d93dc01c68d9e | B80: Chief Operating Officer | C80: Accenture | D80: University of Leuven
A81: 26997a8cf82fd4ef1e85a5dd174e99d4 | B81: Managing Director | C81: Accenture
A82: 269fd93040e4f00403a96052d15cb57a | B82: Head of Accenture Payment Services Nordic | C82: Accenture
A83: 274b4894a1026801539b4c4fcdde8359 | B83: Senior Manager | C83: Accenture
A84: 28bb18f8d9a8427ad2fd21751e0f244a | B84: Director, Accenture Digital | C84: Accenture
A85: 290b956d4d95b1ee6118944a36204350 | B85: Global API Enablement Practice Lead | C85: Accenture
A86: 294edd5bd734fec102360e1c1d02d8b6 | B86: Senior Manager | C86: Accenture | D86: Imperial College Business School University of Nottingham
A87: 29945403e7197c72dc35eb7ba9ddb9c7 | B87: Senior Managing Director, Growth and Strategy Lead and Testing Lead | C87: Accenture | D87: The University of Texas at Arlington
A88: 2a79c941116e9895db2d6eefdad569ad | B88: Managing Director | C88: Accenture
A89: 2ae6a2e956133ffd00c3aca8f3b37cbe | B89: Infrastructure Technical Architecture Associate Manager | C89: Accenture | D89: Wright State University
A90: 2c39fcb99fe5c7be54f74843e58db2d1 | B90: Global Managing Director (France) | C90: Accenture
A91: 2cfe1018c3b5d22542d2cfe2d83f3d1d | B91: Global Lead - Connected Health | C91: Accenture | D91: Dublin Institute of Technology
A92: 2f3b12f4a937693c4bf0caac317356aa | B92: Director, Industry X.0 | C92: Accenture
A93: 2fa7a696963652ddd56b263f6054f93d | B93: Principal Director | C93: Accenture
A94: 3069d1b64e78f2d4504d34048fdfe2db | B94: Chief Research Scientist | C94: Accenture
A95: 31526be9e3c8f5d3d75b70d840a59798 | B95: Senior Managing Director of Global Health Business | C95: Accenture
A96: 3272a6e0b2a618c685d6a88635ef187f | B96: Managing Director at Accenture leading Network Strategy & Global Network Consulting | C96: Accenture | D96: National University of Singapore UCLA Anderson School of Management University of Mumbai University of Southern California
A97: 3298d2c1c57ebff7c7a4906a545a47e1 | B97: Business & Integration Manager | C97: Accenture
A98: 344ff17b29337c058ce41b7a2a4244ee | B98: Managing Director | C98: Accenture
A99: 356ba0a2dd97a76834202d00ed5794e1 | B99: Chief Technology & Information Officer | C99: Accenture | D99: University of Michigan
A100: 3622c3babcfedb95cc1fd34d7dbe1549 | B100: Cloud Security Architect | C100: Accenture
...

Sheet Continents
A1: Country | B1: Continent
A2: Afghanistan | B2: Asia
A3: Albania | B3: Europe
A4: Algeria | B4: Africa
A5: American Samoa | B5: Oceania
A6: Andorra | B6: Europe
A7: Angola | B7: Africa
A8: Anguilla | B8: North America
A9: Antigua and Barbuda | B9: North America
A10: Argentina | B10: South America
A11: Armenia | B11: Asia
A12: Aruba | B12: North America
... A235: Zimbabwe | B235: Africa
